HierVS/__init__.py
HierVS/hierarchicalvs.py
HierVS-1.0.5.dist-info/LICENSE
HierVS-1.0.5.dist-info/METADATA
HierVS-1.0.5.dist-info/WHEEL
HierVS-1.0.5.dist-info/entry_points.txt
HierVS-1.0.5.dist-info/top_level.txt
HierVS-1.0.5.dist-info/RECORD
