Metadata-Version: 2.2
Name: HierVS
Version: 1.0.5
Summary: a fully AI-driven virtual screening package
Author: shukaigu
Author-email: 3160101168@zju.edu.cn
Classifier: Programming Language :: Python :: 3
Classifier: License :: OSI Approved :: MIT License
Classifier: Operating System :: POSIX :: Linux
License-File: LICENSE
Requires-Dist: pandas
Dynamic: author
Dynamic: author-email
Dynamic: classifier
Dynamic: description
Dynamic: description-content-type
Dynamic: requires-dist
Dynamic: summary
